CHANGES.txt
DEPENDENCES.txt
README.txt
setup.py
src/nd/__init__.py
src/nd.hopfield.egg-info/PKG-INFO
src/nd.hopfield.egg-info/SOURCES.txt
src/nd.hopfield.egg-info/dependency_links.txt
src/nd.hopfield.egg-info/namespace_packages.txt
src/nd.hopfield.egg-info/not-zip-safe
src/nd.hopfield.egg-info/requires.txt
src/nd.hopfield.egg-info/top_level.txt
src/nd/hopfield/__init__.py
src/nd/hopfield/hopfield_learn.py
